appletrun/__init__.py
appletrun/__main__.py
appletrun-1.9.6.dist-info/entry_points.txt
appletrun-1.9.6.dist-info/WHEEL
appletrun-1.9.6.dist-info/METADATA
appletrun-1.9.6.dist-info/RECORD
