Metadata-Version: 2.1
Name: appletrun
Version: 1.9.6
Summary: ✨ Appletrun takes java file as input and runs the applet instantly with out manual compilation and html files
Home-page: https://github.com/Royal-lobster/appletrun-python
Keywords: applet,applet run,appletrun
Author: Royal-lobster
Author-email: srujangs8@gmail.com
Requires-Python: >=3.0,<4.0
Classifier: Programming Language :: Python :: 3
Classifier: Programming Language :: Python :: 3.4
Classifier: Programming Language :: Python :: 3.5
Classifier: Programming Language :: Python :: 3.6
Classifier: Programming Language :: Python :: 3.7
Classifier: Programming Language :: Python :: 3.8
Classifier: Programming Language :: Python :: 3.9
Project-URL: Repository, https://github.com/Royal-lobster/appletrun-python
